touchmap/__init__.py
touchmap/encoder.py
touchmap/utils.py
touchmap/grade1map/__init__.py
touchmap/grade1map/binarydict.py
touchmap/grade1map/brailledict.py
touchmap/grade1map/core.py
touchmap/grade2map/__init__.py
touchmap/grade2map/binary2dict.py
touchmap/grade2map/braille2dict.py
touchmap/grade2map/core.py
touchmap/grade2map/word_contract_dict.py
touchmap-0.3.5.dist-info/METADATA
touchmap-0.3.5.dist-info/WHEEL
touchmap-0.3.5.dist-info/licenses/LICENSE
touchmap-0.3.5.dist-info/RECORD
