Metadata-Version: 2.4
Name: touchmap
Version: 0.3.5
Summary: A python library for converting text to braille.
Project-URL: Homepage, https://github.com/Kayak-HSS/touchmap
Project-URL: Repository, https://github.com/Kayak-HSS/touchmap
Project-URL: Issues, https://github.com/Kayak-HSS/touchmap/issues
Author-email: Yajat Pathak <kayakbraillent@gmail.com>
License: Apache-2.0
License-File: LICENSE
Keywords: accessibility,blind,braille,braillent,grade1,grade2,kayak,pybraille,text-to-braille,touchmap,unicode
Classifier: License :: OSI Approved :: Apache Software License
Classifier: Operating System :: OS Independent
Classifier: Programming Language :: Python :: 3
Requires-Python: >=3
Requires-Dist: regex
